qb_ptmap/__init__.py
qb_ptmap/config.py
qb_ptmap/qb_ptmap.py
qb_ptmap-1.0.1.dist-info/WHEEL
qb_ptmap-1.0.1.dist-info/entry_points.txt
qb_ptmap-1.0.1.dist-info/METADATA
qb_ptmap-1.0.1.dist-info/RECORD
