Metadata-Version: 2.3
Name: qb-ptmap
Version: 1.0.1
Summary: Automatic port mapper for qBittorrent with ProtonVPN
Keywords: protonvpn,qbittorrent,vpn,wireguard
Requires-Dist: qbittorrent-api>=2025.7.0
Requires-Python: >=3.12
Project-URL: Documentation, https://github.com/SimoneFelici/qb-ptmap?tab=readme-ov-file#qb-ptmap
Project-URL: Issues, https://github.com/SimoneFelici/qb-ptmap/issues
Project-URL: Repository, https://github.com/SimoneFelici/qb-ptmap
